checkzones/__init__.py
checkzones/checkzones.py
checkzones-0.3.1.dist-info/METADATA
checkzones-0.3.1.dist-info/WHEEL
checkzones-0.3.1.dist-info/entry_points.txt
checkzones-0.3.1.dist-info/RECORD
