Metadata-Version: 2.4
Name: checkzones
Version: 0.3.1
Summary: Check bind zonefiles for validity, to be used in CI/CD pipeline
Author: Alex Kelly
Author-email: alex.kelly@franklin.edu
Requires-Python: >=3.9,<4.0
Classifier: Programming Language :: Python :: 3
Classifier: Programming Language :: Python :: 3.9
Classifier: Programming Language :: Python :: 3.10
Classifier: Programming Language :: Python :: 3.11
Classifier: Programming Language :: Python :: 3.12
Classifier: Programming Language :: Python :: 3.13
Classifier: Programming Language :: Python :: 3.14
Requires-Dist: rich (>=10.9.0,<11.0.0)
